Draw_emoji/Draw_emoji.py
Draw_emoji/__init__.py
Draw_emoji-0.0.1.dist-info/METADATA
Draw_emoji-0.0.1.dist-info/WHEEL
Draw_emoji-0.0.1.dist-info/top_level.txt
Draw_emoji-0.0.1.dist-info/RECORD
