Metadata-Version: 2.1
Name: Draw-emoji
Version: 0.0.1
Summary: A emoji and skin toned emoji extraction package
Home-page: UNKNOWN
Author: Pradhyumna Poralla
Author-email: <pradhyumnaporalla99@gmail.com>
License: UNKNOWN
Keywords: python,emoji,Emoji,skin,Skin,skintoned,Skintoned
Platform: UNKNOWN
Classifier: Development Status :: 1 - Planning
Classifier: Intended Audience :: Developers
Classifier: Programming Language :: Python :: 3
Classifier: Operating System :: Unix
Classifier: Operating System :: MacOS :: MacOS X
Classifier: Operating System :: Microsoft :: Windows
